watchrunner/__init__.py
watchrunner/core.py
watchrunner-0.1.1.dist-info/licenses/LICENSE
watchrunner-0.1.1.dist-info/METADATA
watchrunner-0.1.1.dist-info/WHEEL
watchrunner-0.1.1.dist-info/entry_points.txt
watchrunner-0.1.1.dist-info/top_level.txt
watchrunner-0.1.1.dist-info/RECORD
