Metadata-Version: 2.4
Name: watchrunner
Version: 0.1.1
Summary: A Python file watcher that auto-restarts your script on change.
Author-email: ahmed-assan <ahmed2001365618@gmail.com>
License: MIT License
Project-URL: Homepage, https://github.com/ahmed2001365618/watchrunner
Classifier: Programming Language :: Python :: 3
Classifier: License :: OSI Approved :: MIT License
Classifier: Operating System :: OS Independent
Requires-Python: >=3.9
License-File: LICENSE
Requires-Dist: watchdog
Dynamic: license-file
